fastopic/FASTopic.py
fastopic/_ETP.py
fastopic/__init__.py
fastopic/_fastopic.py
fastopic/_model_utils.py
fastopic/_plot.py
fastopic/_utils.py
fastopic-1.0.1.dist-info/licenses/LICENSE
fastopic-1.0.1.dist-info/METADATA
fastopic-1.0.1.dist-info/WHEEL
fastopic-1.0.1.dist-info/top_level.txt
fastopic-1.0.1.dist-info/RECORD
