Metadata-Version: 2.4
Name: fastopic
Version: 1.0.1
Summary: FASTopic
Author-email: Xiaobao Wu <xiaobao002@e.ntu.edu.sg>
License: Apache 2.0 License
Project-URL: Homepage, https://github.com/bobxwu/fastopic
Project-URL: Repository, https://github.com/bobxwu/fastopic.git
Project-URL: Issues, https://github.com/bobxwu/fastopic/issues
Keywords: toolkit,topic model,neural topic model,bert,semantics,text processing,text analysis
Requires-Python: >=3.9
License-File: LICENSE
Requires-Dist: topmost>=1.0.2
Provides-Extra: test
Requires-Dist: pytest>=8.3.0; extra == "test"
Dynamic: license-file
